line_track_designer/__init__.py
line_track_designer/cli.py
line_track_designer/error.py
line_track_designer/markdown.py
line_track_designer/printer.py
line_track_designer/tile.py
line_track_designer/track.py
line_track_designer/pdf/linefollowtiles.pdf
line_track_designer/png/linefollowtiles-01.png
line_track_designer/png/linefollowtiles-02.png
line_track_designer/png/linefollowtiles-03.png
line_track_designer/png/linefollowtiles-04.png
line_track_designer/png/linefollowtiles-05.png
line_track_designer/png/linefollowtiles-06.png
line_track_designer/png/linefollowtiles-07.png
line_track_designer/png/linefollowtiles-08.png
line_track_designer/png/linefollowtiles-09.png
line_track_designer/png/linefollowtiles-11.png
line_track_designer/png/linefollowtiles-12.png
line_track_designer/png/linefollowtiles-13.png
line_track_designer/png/linefollowtiles-14.png
line_track_designer/png/linefollowtiles-15.png
line_track_designer/png/linefollowtiles-16.png
line_track_designer/png/linefollowtiles-17.png
line_track_designer/png/linefollowtiles-18.png
line_track_designer/png/linefollowtiles-19.png
line_track_designer/png/linefollowtiles-20.png
line_track_designer/png/linefollowtiles-21.png
line_track_designer/png/linefollowtiles-22.png
line_track_designer/png/linefollowtiles-23.png
line_track_designer/png/linefollowtiles-24.png
line_track_designer/png/linefollowtiles-25.png
line_track_designer/png/linefollowtiles-26.png
line_track_designer/png/linefollowtiles-27.png
line_track_designer/png/linefollowtiles-28.png
line_track_designer/png/linefollowtiles-29.png
line_track_designer/png/linefollowtiles-30.png
line_track_designer/png/linefollowtiles-31.png
line_track_designer/png/linefollowtiles-32.png
line_track_designer/png/linefollowtiles-33.png
line_track_designer-0.0.2.dist-info/LICENSE
line_track_designer-0.0.2.dist-info/METADATA
line_track_designer-0.0.2.dist-info/WHEEL
line_track_designer-0.0.2.dist-info/entry_points.txt
line_track_designer-0.0.2.dist-info/top_level.txt
line_track_designer-0.0.2.dist-info/zip-safe
line_track_designer-0.0.2.dist-info/RECORD
