Metadata-Version: 2.1
Name: line-track-designer
Version: 0.0.2
Summary: A library to design line following tracks for robots
Home-page: https://github.com/Quentin18/Line-Track-Designer/
Author: Quentin Deschamps
Author-email: quentindeschamps18@gmail.com
License: MIT
Project-URL: Documentation, https://line-track-designer.readthedocs.io/en/latest/
Project-URL: Travis, https://travis-ci.org/github/Quentin18/Line-Track-Designer/
Project-URL: Source Code, https://github.com/Quentin18/Line-Track-Designer/
Keywords: robotics line follow robot track
Platform: any
Classifier: License :: OSI Approved :: MIT License
Classifier: Natural Language :: English
Classifier: Operating System :: OS Independent
Classifier: Programming Language :: Python :: 3.6
Classifier: Programming Language :: Python :: 3.7
Classifier: Programming Language :: Python :: 3.8
Classifier: Topic :: Education
Classifier: Topic :: Scientific/Engineering
Requires-Python: >=3.6
Requires-Dist: Click
Requires-Dist: Pillow
Requires-Dist: numpy
Requires-Dist: pycups ; platform_system != "Windows"
